[
    {
      "_id": "623853b2614ad5aba311fdd1",
      "index": 0,
      "price": 14,
      "picture": "https://i.pinimg.com/originals/9f/3d/13/9f3d13912d3cf78e4c87975bcebc1fee.jpg",
      "name": "Just Chill 01",
      "gender": "Just Chill",
      "title": "Impressive Performance",
      "rating": 4.8,
      "author": "Sarah Johnson",
      "date": "2023-06-18"
    },
    {
      "_id": "623853b2578e9e6ad1ae0dd5",
      "index": 1,
      "picture": "https://render.fineartamerica.com/images/rendered/default/t-shirt/23/30/images/artworkimages/medium/1/coffee-coding-syntax-aadil-farooq-transparent.png?targetx=0&targety=0&imagewidth=430&imageheight=516&modelwidth=430&modelheight=575",
      "name": "Keep Coding 02",
      "price": 27,
      "gender": "Keep Coding",
      "rating": 3.5,
      "author": "Michael Smith",
      "date": "2023-06-17"
    },
    {
      "_id": "623853b21fb149d2ee7b76c7",
      "index": 2,
      "picture": "https://images.unsplash.com/photo-1583743814966-8936f5b7be1a?ixlib=rb-1.2.1&ixid=MnwxMjA3fDB8MHxzZWFyY2h8NXx8dCUyMHNoaXJ0fGVufDB8fDB8fA%3D%3D&auto=format&fit=crop&w=500&q=60",
      "name": "Black 03",
      "price": 24,
      "gender": "",
      "rating": 2.2,
  "author": "Emily Wilson",
  "date": "2023-06-16"
    },
    {
      "_id": "623853b2e91c8de578c9245e",
      "index": 3,
      "picture": "https://5.imimg.com/data5/SH/GC/MY-8764775/mens-t-shirt-500x500.jpg",
      "name": "Mix Yellow 04",
      "price": 14,
      "gender": "Mix Yellow",
      "rating": 4.9,
      "author": "David Thompson",
      "date": "2023-06-14"
    },
    {
      "_id": "623853b2239582e48409ccc6",
      "index": 4,
      "price": 34,
      "picture": "https://www.billbazar.com.bd/public/uploads/all/8hgD0lQGODVXbB5sokhvwr7mUNjBx7pEHusuyGZj.webp",
      "name": "Bachelor 05",
      "gender": "male",
      "rating": 4.0,
  "author": "Amy Anderson",
  "date": "2023-06-12"
    },
    {
      "_id": "623853b2cdda0d5bc294f791",
      "index": 5,
      "picture": "https://m.media-amazon.com/images/I/61GMJ+3ekAS._AC_UL320_.jpg",
      "name": "Right Price 06",
      "price": 141,
      "gender": "male",
      "rating": 4.7,
  "author": "Mark Davis",
  "date": "2023-06-10"
    },
    {
      "_id": "623853b2736f19fd4eb8d44a",
      "index": 6,
      "price": 41,
      "picture": "https://i.pinimg.com/236x/af/96/95/af9695e0116a1d859336024e6cdcea10.jpg",
      "name": "Black Skull 07",
      "gender": "female",
      "rating": 4.6,
  "author": "Jennifer Lee",
  "date": "2023-06-08"
    },
    {
        "_id": "623853b2614ad5aba311fdd1",
        "index": 0,
        "price": 14,
        "picture": "https://i.pinimg.com/originals/9f/3d/13/9f3d13912d3cf78e4c87975bcebc1fee.jpg",
        "name": "Just Chill 08",
        "gender": "Just Chill",
        "rating": 2.0,
        "author": "Robert Johnson",
        "date": "2023-06-05"
      },
      {
        "_id": "623853b2578e9e6ad1ae0dd5",
        "index": 1,
        "picture": "https://render.fineartamerica.com/images/rendered/default/t-shirt/23/30/images/artworkimages/medium/1/coffee-coding-syntax-aadil-farooq-transparent.png?targetx=0&targety=0&imagewidth=430&imageheight=516&modelwidth=430&modelheight=575",
        "name": "Keep Coding 09",
        "price": 27,
        "gender": "Keep Coding",
        "rating": 3.3,
  "author": "Karen Thompson",
  "date": "2023-06-03"
      },
      {
        "_id": "623853b21fb149d2ee7b76c7",
        "index": 2,
        "picture": "https://images.unsplash.com/photo-1583743814966-8936f5b7be1a?ixlib=rb-1.2.1&ixid=MnwxMjA3fDB8MHxzZWFyY2h8NXx8dCUyMHNoaXJ0fGVufDB8fDB8fA%3D%3D&auto=format&fit=crop&w=500&q=60",
        "name": "Black 10",
        "price": 24,
        "gender": "",
        "rating": 4.4,
  "author": "James Wilson",
  "date": "2023-06-01"
      },
      {
        "_id": "623853b2e91c8de578c9245e",
        "index": 3,
        "picture": "https://5.imimg.com/data5/SH/GC/MY-8764775/mens-t-shirt-500x500.jpg",
        "name": "Mix Yellow 11",
        "price": 14,
        "gender": "Mix Yellow",
        "rating": 3.8,
  "author": "Laura Anderson",
  "date": "2023-05-29"
      },
      {
        "_id": "623853b2239582e48409ccc6",
        "index": 4,
        "price": 34,
        "picture": "https://www.billbazar.com.bd/public/uploads/all/8hgD0lQGODVXbB5sokhvwr7mUNjBx7pEHusuyGZj.webp",
        "name": "Bachelor 12",
        "gender": "male",
        "title": "Feature-Packed Flagship",
  "rating": 4.9,
  "author": "Daniel Smith",
  "date": "2023-05-27"
      },
      {
        "_id": "623853b2cdda0d5bc294f791",
        "index": 5,
        "picture": "https://m.media-amazon.com/images/I/61GMJ+3ekAS._AC_UL320_.jpg",
        "name": "Right Price 13",
        "price": 141,
        "gender": "male",
        "rating": 4.8,
  "author": "Jessica Thompson",
  "date": "2023-05-25"
      },
      {
        "_id": "623853b2736f19fd4eb8d44a",
        "index": 6,
        "price": 41,
        "picture": "https://i.pinimg.com/236x/af/96/95/af9695e0116a1d859336024e6cdcea10.jpg",
        "name": "Black Skull 14",
        "gender": "female",
        "rating": 3.2,
        "author": "Kevin Davis",
        "date": "2023-05-23"
      }
  ]